MANIFEST.in
README.md
build.py
setup.py
/home/riceric22/pytorch_fft/pytorch_fft/src/th_fft_cuda.c
pytorch_fft/__init__.py
pytorch_fft.egg-info/PKG-INFO
pytorch_fft.egg-info/SOURCES.txt
pytorch_fft.egg-info/dependency_links.txt
pytorch_fft.egg-info/requires.txt
pytorch_fft.egg-info/top_level.txt
pytorch_fft/_ext/__init__.py
pytorch_fft/_ext/th_fft/__init__.py
pytorch_fft/fft/__init__.py
pytorch_fft/fft/autograd.py
pytorch_fft/fft/fft.py
pytorch_fft/src/th_fft_cuda.c
pytorch_fft/src/th_fft_cuda.h
pytorch_fft/src/th_fft_generate_double.h
pytorch_fft/src/th_fft_generate_float.h
pytorch_fft/src/th_fft_generate_helpers.h
pytorch_fft/src/generic/helpers.c
pytorch_fft/src/generic/th_fft_cuda.c
pytorch_fft/src/generic/th_fft_cuda.h
pytorch_fft/src/generic/th_irfft_cuda.c
pytorch_fft/src/generic/th_rfft_cuda.c