Metadata-Version: 1.0
Name: pytorch-fft
Version: 0.15
Summary: A PyTorch wrapper for CUDA FFTs
Home-page: https://github.com/locuslab/pytorch_fft
Author: Eric Wong
Author-email: ericwong@cs.cmu.edu
License: UNKNOWN
Platform: UNKNOWN
